{
    "data":[
        {
            "php":"admin/shell/shell.php",
            "css":["shell.css"],
            "js":"",
            "jquery":[],
            "permisos":[1,2],
            "constante":"SHELL",
            "url":"admin/shell/",
            "nombre":"Consola de comandos",
            "ajax":["base/ajax.admin.js","blog/ajax.admin.js"],
            "status":1,
            "editable":0,
            "modulo":"developer"
        },
        {
            "php":"admin/franky/lista.php",
            "css":"",
            "js":[],
            "jquery":[],
            "permisos":[1],
            "constante":"LISTA_PAGINAS",
            "url":"admin/paginas/",
            "nombre":"Páginas",
            "ajax":["base/ajax.admin.js"],
            "status":1,
            "editable":1,
            "modulo":"developer"
        },
        {
            "php":"admin/franky/form.php",
            "css":"",
            "js":["validaciones.js"],
            "jquery":["jquery-validate"],
            "permisos":[1],
            "constante":"FRM_PAGINAS",
            "url":"admin/paginas/frm/",
            "nombre":"Alta de paginas",
            "ajax":[],
            "status":1,
            "editable":1,
            "modulo":"developer"
        },
        {
            "php":"admin/ftp/ftp.php",
            "css":["shell.css"],
            "js":[],
            "jquery":["jquery-validate"],
            "permisos":[1,2],
            "constante":"ADMIN_FTP",
            "url":"admin/ftp/",
            "nombre":"FTP",
            "ajax":["developer/ajax.ftp.js"],
            "status":1,
            "editable":0,
            "modulo":"developer"
        },
        {
            "php":"admin/custom_attributes/form.php",
            "css":"",
            "js":["validaciones.js"],
            "jquery":["jquery-validate"],
            "permisos":[1,2],
            "constante":"FRM_CUSTOM_ATTRIBUTES",
            "url":"admin/custom-attributes/frm/",
            "nombre":"Alta de atributos personalizados",
            "ajax":[],
            "status":1,
            "editable":0,
            "modulo":"developer"
        },
        {
            "php":"admin/custom_attributes/lista.php",
            "css":"",
            "js":[],
            "jquery":[],
            "permisos":[1,2],
            "constante":"ADMIN_CUSTOM_ATTRIBUTES",
            "url":"admin/custom-attributes/",
            "nombre":"Atributos personalizados",
            "ajax":["base/ajax.admin.js"],
            "status":1,
            "editable":0,
            "modulo":"developer"
        }
    ]
}
